[
  {"1":"CHIEFCHIRPA", 
   "2":"WICKET",
   "3":"EWOKELDER",
   "4":"LOGRAY",
   "5":"PAPLOO"
  },
  {"1":"MAUL", 
   "2":"SAVAGEOPRESS",
   "3":"SITHASSASSIN",
   "4":"COUNTDOOKU",
   "5":"SITHMARAUDER"
  },
  {"1":"SHAAKTI", 
   "2":"CT5555",
   "3":"CT210408",
   "4":"CT7567",
   "5":"CLONESERGEANTPHASEI"
  },
  {"1":"NUTEGUNRAY", 
   "2":"COUNTDOOKU",
   "3":"GEONOSIANSOLDIER",
   "4":"GEONOSIANSPY",
   "5":"SUNFAC"
  },
  {"1":"WEDGEANTILLES", 
   "2":"BIGGSDARKLIGHTER",
   "3":"CHIRRUTIMWE",
   "4":"BAZEMALBUS",
   "5":"PRINCESSLEIA"
  },
  {"1":"HERASYNDULLAS3", 
   "2":"ZEBS3",
   "3":"KANANJARRUSS3",
   "4":"SABINEWRENS3",
   "5":"CHOPPERS3"
  },
  {"1":"JYNERSO", 
   "2":"CASSIANANDOR",
   "3":"K2SO",
   "4":"CHIRRUTIMWE",
   "5":"BAZEMALBUS",
  }
]